napari_skimage/__init__.py
napari_skimage/_version.py
napari_skimage/axis_ops.py
napari_skimage/mathsops.py
napari_skimage/napari.yaml
napari_skimage/skimage_detection_widget.py
napari_skimage/skimage_filter_widget.py
napari_skimage/skimage_label_widget.py
napari_skimage/skimage_morphology_widget.py
napari_skimage/skimage_regionprops_widget.py
napari_skimage/skimage_restoration_widget.py
napari_skimage/skimage_threshold_widget.py
napari_skimage/_tests/__init__.py
napari_skimage/_tests/test_axis_widgets.py
napari_skimage/_tests/test_basic_widgets.py
napari_skimage/_tests/test_detection_widgets.py
napari_skimage/_tests/test_regionprops_widget.py
napari_skimage-0.6.0.dist-info/licenses/LICENSE
napari_skimage-0.6.0.dist-info/METADATA
napari_skimage-0.6.0.dist-info/WHEEL
napari_skimage-0.6.0.dist-info/entry_points.txt
napari_skimage-0.6.0.dist-info/top_level.txt
napari_skimage-0.6.0.dist-info/RECORD
